metis_app/__init__.py
metis_app/app.py
metis_app/app_events.py
metis_app/app_route.py
metis_app/app_serialisers.py
metis_app/app_value.py
metis_app/app_web_session.py
metis_app/aws_client_helpers.py
metis_app/cache.py
metis_app/circuit.py
metis_app/coerser.py
metis_app/crypto.py
metis_app/crypto_util/common.py
metis_app/crypto_util/jwa.py
metis_app/crypto_util/jwe.py
metis_app/crypto_util/jwk.py
metis_app/crypto_util/jws.py
metis_app/crypto_util/jwt.py
metis_app/env.py
metis_app/error.py
metis_app/http.py
metis_app/http_adapter.py
metis_app/json_util.py
metis_app/logger.py
metis_app/observable.py
metis_app/parameter_store.py
metis_app/pdp.py
metis_app/pip.py
metis_app/random_retry_window.py
metis_app/self_token.py
metis_app/span_tracer.py
metis_app/state_machine.py
metis_app/subject_token.py
metis_app/tracer.py
metis_app-1.1.0.dist-info/METADATA
metis_app-1.1.0.dist-info/WHEEL
metis_app-1.1.0.dist-info/RECORD
