Metadata-Version: 2.1
Name: metis-app
Version: 1.1.0
Summary: 
Author: Col Perks
Author-email: wild.fauve@gmail.com
Requires-Python: >=3.11,<4.0
Classifier: Programming Language :: Python :: 3
Classifier: Programming Language :: Python :: 3.11
Classifier: Programming Language :: Python :: 3.12
Requires-Dist: backoff (>=2.2.1,<3.0.0)
Requires-Dist: cryptography (>=44.0.0,<45.0.0)
Requires-Dist: metis-fn (>=0.1.1,<0.2.0)
Requires-Dist: pino (>=0.6.0,<0.7.0)
Requires-Dist: requests (>=2.31.0,<3.0.0)
Requires-Dist: simple-memory-cache (>=1.0.0,<2.0.0)
